EGGcodepy/EGGcodepy.py
EGGcodepy/__init__.py
EGGcodepy-0.0.1.dist-info/LICENSE
EGGcodepy-0.0.1.dist-info/METADATA
EGGcodepy-0.0.1.dist-info/WHEEL
EGGcodepy-0.0.1.dist-info/top_level.txt
EGGcodepy-0.0.1.dist-info/RECORD
